aiosteamist/__init__.py
aiosteamist/py.typed
aiosteamist-1.0.0.dist-info/LICENSE
aiosteamist-1.0.0.dist-info/METADATA
aiosteamist-1.0.0.dist-info/WHEEL
aiosteamist-1.0.0.dist-info/RECORD
