Metadata-Version: 2.1
Name: aiosteamist
Version: 1.0.0
Summary: Control Steamist steam systems
Home-page: https://github.com/bdraco/aiosteamist
Author: J. Nick Koston
Author-email: nick@koston.org
Requires-Python: >=3.10,<4.0
Classifier: Development Status :: 2 - Pre-Alpha
Classifier: Intended Audience :: Developers
Classifier: License :: OSI Approved :: Apache Software License
Classifier: Natural Language :: English
Classifier: Operating System :: OS Independent
Classifier: Programming Language :: Python :: 3
Classifier: Programming Language :: Python :: 3.10
Classifier: Programming Language :: Python :: 3.11
Classifier: Programming Language :: Python :: 3.12
Classifier: Topic :: Software Development :: Libraries
Provides-Extra: docs
Requires-Dist: Sphinx (>=5.0.0) ; extra == "docs"
Requires-Dist: aiohttp (>=3.9.1)
Requires-Dist: myst-parser (>=0.16.0) ; extra == "docs"
Requires-Dist: sphinx-rtd-theme (>=1.0.0) ; extra == "docs"
Requires-Dist: xmltodict (>=0.12.0)
Project-URL: Bug Tracker, https://github.com/bdraco/aiosteamist/issues
Project-URL: Changelog, https://aiosteamist.readthedocs.io/changelog.html
Project-URL: Documentation, https://aiosteamist.readthedocs.io
Project-URL: Repository, https://github.com/bdraco/aiosteamist
